[
  {
    "A": "Artist_Name",
    "B": "Today_Score",
    "C": "Image_Url"
  },
  {
    "A": "AYN",
    "B": "1056",
    "C": "https://placehold.co/300x300/1d4436/69e091?text=A"
  },
  {
    "A": "Santhanam",
    "B": "578",
    "C": "https://placehold.co/300x300/1d4436/69e091?text=S"
  },
  {
    "A": "Sarah Black",
    "B": "290",
    "C": "https://placehold.co/300x300/1d4436/69e091?text=S+B"
  },
  {
    "A": "Reema",
    "B": "56",
    "C": "https://placehold.co/300x300/1d4436/69e091?text=R"
  },
  {
    "A": "Poorna M",
    "B": "35",
    "C": "https://placehold.co/300x300/1d4436/69e091?text=P+M"
  },
  {
    "A": "Daryion",
    "B": "28",
    "C": "https://placehold.co/300x300/1d4436/69e091?text=D"
  },
  {
    "A": "Jai",
    "B": "25",
    "C": "https://placehold.co/300x300/1d4436/69e091?text=J"
  },
  {
    "A": "John Mayer",
    "B": "22",
    "C": "https://placehold.co/300x300/1d4436/69e091?text=J+M"
  },
  {
    "A": "Achint",
    "B": "0",
    "C": "https://placehold.co/300x300/1d4436/69e091?text=A"
  },
  {
    "A": "Ankit Tiwari",
    "B": "0",
    "C": "https://placehold.co/300x300/1d4436/69e091?text=A+T"
  },
  {
    "A": "Deva",
    "B": "0",
    "C": "https://placehold.co/300x300/1d4436/69e091?text=D"
  },
  {
    "A": "Maran",
    "B": "0",
    "C": "https://placehold.co/300x300/1d4436/69e091?text=M"
  },
  {
    "A": "Mehmood",
    "B": "0",
    "C": "https://placehold.co/300x300/1d4436/69e091?text=M"
  },
  {
    "A": "Paraforce",
    "B": "0",
    "C": "https://placehold.co/300x300/1d4436/69e091?text=P"
  },
  {
    "A": "Shubha",
    "B": "0",
    "C": "https://placehold.co/300x300/1d4436/69e091?text=S"
  }
]